LICENSE.txt
MANIFEST.in
README.rst
setup.cfg
setup.py
aserializer/__init__.py
aserializer/base.py
aserializer.egg-info/PKG-INFO
aserializer.egg-info/SOURCES.txt
aserializer.egg-info/dependency_links.txt
aserializer.egg-info/top_level.txt
aserializer/collection/__init__.py
aserializer/collection/base.py
aserializer/django/__init__.py
aserializer/django/collection.py
aserializer/django/fields.py
aserializer/django/mixins.py
aserializer/django/serializers.py
aserializer/django/utils.py
aserializer/fields/__init__.py
aserializer/fields/base.py
aserializer/fields/fields.py
aserializer/fields/serializer_fields.py
aserializer/fields/time_fields.py
aserializer/fields/validators.py
aserializer/mongoengine/__init__.py
aserializer/mongoengine/collection.py
aserializer/utils/__init__.py
aserializer/utils/options.py
aserializer/utils/parsers.py
aserializer/utils/py2to3.py
aserializer/utils/registry.py